glue_wwt/__init__.py
glue_wwt/conftest.py
glue_wwt/version.py
glue_wwt/viewer/__init__.py
glue_wwt/viewer/data_viewer.py
glue_wwt/viewer/image_layer.py
glue_wwt/viewer/image_style_editor.py
glue_wwt/viewer/image_style_editor.ui
glue_wwt/viewer/jupyter_viewer.py
glue_wwt/viewer/layer_artist.py
glue_wwt/viewer/options_widget.py
glue_wwt/viewer/options_widget.ui
glue_wwt/viewer/qt_data_viewer.py
glue_wwt/viewer/state.py
glue_wwt/viewer/table_layer.py
glue_wwt/viewer/table_style_editor.py
glue_wwt/viewer/table_style_editor.ui
glue_wwt/viewer/tools.py
glue_wwt/viewer/utils.py
glue_wwt/viewer/viewer_state.py
glue_wwt/viewer/wwt_icon.png
glue_wwt/viewer/tests/__init__.py
glue_wwt/viewer/tests/test_utils.py
glue_wwt/viewer/tests/test_wwt_widget.py
glue_wwt/viewer/tests/data/wwt_simple.glu
glue_wwt-0.7.2.dist-info/LICENSE
glue_wwt-0.7.2.dist-info/METADATA
glue_wwt-0.7.2.dist-info/WHEEL
glue_wwt-0.7.2.dist-info/entry_points.txt
glue_wwt-0.7.2.dist-info/top_level.txt
glue_wwt-0.7.2.dist-info/RECORD
