Metadata-Version: 2.1
Name: glue-wwt
Version: 0.7.2
Summary: Glue WorldWide Telescope plugin
Author-email: Thomas Robitaille <thomas.robitaille@gmail.com>
License: BSD 3-Clause License
Project-URL: Homepage, https://github.com/glue-viz/glue-wwt
Requires-Python: >=3.8
License-File: LICENSE
Requires-Dist: numpy
Requires-Dist: glue-core >=1.13.1
Requires-Dist: echo
Requires-Dist: astropy
Requires-Dist: pywwt >=0.21.0
Requires-Dist: packaging
Provides-Extra: qt
Requires-Dist: qtpy ; extra == 'qt'
Requires-Dist: glue-qt ; extra == 'qt'
Requires-Dist: PyQt5 ; (python_version >= "3") and extra == 'qt'
Requires-Dist: PyQtWebEngine ; (python_version >= "3") and extra == 'qt'
Provides-Extra: test
Requires-Dist: pytest ; extra == 'test'
Requires-Dist: pytest-cov ; extra == 'test'
Requires-Dist: mock ; extra == 'test'
